[
  {
    "ContainingType": "Restaurents.API.Controllers.RestaurantsController",
    "Method": "GetAll",
    "RelativePath": "api/restaurants",
    "HttpMethod": "GET",
    "IsController": true,
    "Order": 0,
    "Parameters": [],
    "ReturnTypes": [
      {
        "Type": "System.Collections.Generic.IEnumerable\u00601[[Restaurants.Application.Restaurants.Dtos.RestaurantDto, Restaurants.Application, Version=1.0.0.0, Culture=neutral, PublicKeyToken=null]]",
        "MediaTypes": [
          "text/plain",
          "application/json",
          "text/json"
        ],
        "StatusCode": 200
      }
    ]
  },
  {
    "ContainingType": "Restaurents.API.Controllers.RestaurantsController",
    "Method": "CreateRestaurant",
    "RelativePath": "api/restaurants",
    "HttpMethod": "POST",
    "IsController": true,
    "Order": 0,
    "Parameters": [
      {
        "Name": "createRestaurant",
        "Type": "Restaurants.Application.Restaurants.Commands.CreateRestaurant.CreateRestaurantCommand",
        "IsRequired": true
      }
    ],
    "ReturnTypes": []
  },
  {
    "ContainingType": "Restaurents.API.Controllers.RestaurantsController",
    "Method": "GetRestaurantById",
    "RelativePath": "api/restaurants/{RestaurantId}",
    "HttpMethod": "GET",
    "IsController": true,
    "Order": 0,
    "Parameters": [
      {
        "Name": "RestaurantId",
        "Type": "System.Int32",
        "IsRequired": true
      }
    ],
    "ReturnTypes": [
      {
        "Type": "Restaurants.Domain.Entities.Restaurant",
        "MediaTypes": [
          "text/plain",
          "application/json",
          "text/json"
        ],
        "StatusCode": 200
      }
    ]
  },
  {
    "ContainingType": "Restaurents.API.Controllers.RestaurantsController",
    "Method": "DeleteRestaurant",
    "RelativePath": "api/restaurants/{RestaurantId}",
    "HttpMethod": "DELETE",
    "IsController": true,
    "Order": 0,
    "Parameters": [
      {
        "Name": "RestaurantId",
        "Type": "System.Int32",
        "IsRequired": true
      }
    ],
    "ReturnTypes": [
      {
        "Type": "Microsoft.AspNetCore.Mvc.ProblemDetails",
        "MediaTypes": [
          "text/plain",
          "application/json",
          "text/json"
        ],
        "StatusCode": 404
      }
    ]
  },
  {
    "ContainingType": "Restaurents.API.Controllers.RestaurantsController",
    "Method": "UpdateRestaurant",
    "RelativePath": "api/restaurants/{RestaurantId}",
    "HttpMethod": "PATCH",
    "IsController": true,
    "Order": 0,
    "Parameters": [
      {
        "Name": "RestaurantId",
        "Type": "System.Int32",
        "IsRequired": true
      },
      {
        "Name": "command",
        "Type": "Restaurants.Application.Restaurants.Commands.UpdateRestaurant.UpdateRestaurantCommand",
        "IsRequired": true
      }
    ],
    "ReturnTypes": [
      {
        "Type": "System.Void",
        "MediaTypes": [],
        "StatusCode": 204
      },
      {
        "Type": "Microsoft.AspNetCore.Mvc.ProblemDetails",
        "MediaTypes": [
          "text/plain",
          "application/json",
          "text/json"
        ],
        "StatusCode": 404
      }
    ]
  },
  {
    "ContainingType": "Restaurents.API.Controllers.DishController",
    "Method": "CreateDishes",
    "RelativePath": "api/restaurants/{restaurantId}/dishes",
    "HttpMethod": "POST",
    "IsController": true,
    "Order": 0,
    "Parameters": [
      {
        "Name": "restaurantId",
        "Type": "System.Int32",
        "IsRequired": true
      },
      {
        "Name": "command",
        "Type": "Restaurants.Application.Dishes.Commands.CreateDishes.CreateDishesCommand",
        "IsRequired": true
      }
    ],
    "ReturnTypes": []
  },
  {
    "ContainingType": "Restaurents.API.Controllers.DishController",
    "Method": "GetAllDishesForRestaurant",
    "RelativePath": "api/restaurants/{restaurantId}/dishes",
    "HttpMethod": "GET",
    "IsController": true,
    "Order": 0,
    "Parameters": [
      {
        "Name": "restaurantId",
        "Type": "System.Int32",
        "IsRequired": true
      }
    ],
    "ReturnTypes": [
      {
        "Type": "System.Collections.Generic.IEnumerable\u00601[[Restaurants.Application.Dishes.Dtos.DishesDto, Restaurants.Application, Version=1.0.0.0, Culture=neutral, PublicKeyToken=null]]",
        "MediaTypes": [
          "text/plain",
          "application/json",
          "text/json"
        ],
        "StatusCode": 200
      }
    ]
  },
  {
    "ContainingType": "Restaurents.API.Controllers.DishController",
    "Method": "DeleteAllDishForRestaurant",
    "RelativePath": "api/restaurants/{restaurantId}/dishes",
    "HttpMethod": "DELETE",
    "IsController": true,
    "Order": 0,
    "Parameters": [
      {
        "Name": "restaurantId",
        "Type": "System.Int32",
        "IsRequired": true
      }
    ],
    "ReturnTypes": []
  },
  {
    "ContainingType": "Restaurents.API.Controllers.DishController",
    "Method": "GetSpecificDishForRestaurant",
    "RelativePath": "api/restaurants/{restaurantId}/dishes/{dishId}",
    "HttpMethod": "GET",
    "IsController": true,
    "Order": 0,
    "Parameters": [
      {
        "Name": "restaurantId",
        "Type": "System.Int32",
        "IsRequired": true
      },
      {
        "Name": "dishId",
        "Type": "System.Int32",
        "IsRequired": true
      }
    ],
    "ReturnTypes": [
      {
        "Type": "Restaurants.Application.Dishes.Dtos.DishesDto",
        "MediaTypes": [
          "text/plain",
          "application/json",
          "text/json"
        ],
        "StatusCode": 200
      }
    ]
  },
  {
    "ContainingType": "Restaurents.API.Controllers.DishController",
    "Method": "DeleteDishForRestaurant",
    "RelativePath": "api/restaurants/{restaurantId}/dishes/{dishId}",
    "HttpMethod": "DELETE",
    "IsController": true,
    "Order": 0,
    "Parameters": [
      {
        "Name": "restaurantId",
        "Type": "System.Int32",
        "IsRequired": true
      },
      {
        "Name": "dishId",
        "Type": "System.Int32",
        "IsRequired": true
      }
    ],
    "ReturnTypes": []
  }
]